.gitignore
LICENSE
README.md
commond.txt
setup.py
pygibberish/__init__.py
pygibberish/__init__.pyc
pygibberish/_train_all.py
pygibberish.egg-info/PKG-INFO
pygibberish.egg-info/SOURCES.txt
pygibberish.egg-info/dependency_links.txt
pygibberish.egg-info/top_level.txt
pygibberish/train_data/ch_bad.txt
pygibberish/train_data/ch_big.txt
pygibberish/train_data/ch_good.txt
pygibberish/train_data/en_bad.txt
pygibberish/train_data/en_big.txt
pygibberish/train_data/en_good.txt